idebug/__init__.py
idebug-2.4.1.dist-info/LICENSE
idebug-2.4.1.dist-info/METADATA
idebug-2.4.1.dist-info/WHEEL
idebug-2.4.1.dist-info/top_level.txt
idebug-2.4.1.dist-info/RECORD
