Metadata-Version: 2.1
Name: idebug
Version: 2.4.1
Summary: 디버깅용
Home-page: https://github.com/innovata/idebug
Author: innovata sambong
Author-email: innovata <innovata@gmail.com>
Project-URL: Homepage, https://github.com/innovata/idebug
Project-URL: Bug Tracker, https://github.com/innovata/idebug/issues
Classifier: Programming Language :: Python :: 3
Classifier: License :: OSI Approved :: MIT License
Classifier: Operating System :: OS Independent
Requires-Python: >=3.8
License-File: LICENSE
